dj_static.py
dj_static_incuna-0.0.6.dist-info/DESCRIPTION.rst
dj_static_incuna-0.0.6.dist-info/metadata.json
dj_static_incuna-0.0.6.dist-info/top_level.txt
dj_static_incuna-0.0.6.dist-info/METADATA
dj_static_incuna-0.0.6.dist-info/WHEEL
dj_static_incuna-0.0.6.dist-info/RECORD
