Metadata-Version: 2.0
Name: dj-static-incuna
Version: 0.0.6
Summary: Serve production static files with Django.
Home-page: https://github.com/incuna/dj-static
Author: Kenneth Reitz
Author-email: me@kennethreitz.com
License: BSD
Platform: any
Classifier: Environment :: Web Environment
Classifier: Intended Audience :: Developers
Classifier: License :: OSI Approved :: BSD License
Classifier: Operating System :: OS Independent
Classifier: Programming Language :: Python
Classifier: Topic :: Internet :: WWW/HTTP :: Dynamic Content
Classifier: Topic :: Software Development :: Libraries :: Python Modules
Requires-Dist: static3
